<JobPostResponse xmlns:i="http://www.w3.org/2001/XMLSchema-instance" xmlns="http://schemas.servicestack.net/types"><ResponseCode xmlns="http://schemas.datacontract.org/2004/07/JXTPlatform.DTO.Base">SUCCESS</ResponseCode><ResponseMessage xmlns="http://schemas.datacontract.org/2004/07/JXTPlatform.DTO.Base" /><Summary><DateCreated>2016-04-18T16:51:46.63</DateCreated><FinishedDate>2016-04-18T16:51:47.443</FinishedDate><Inserted>0</Inserted><Sent>1</Sent><Updated>1</Updated><Archived>0</Archived><Failed>0</Failed></Summary><JobPosting><Job><Action>UPDATE</Action><ReferenceNo>28777-1</ReferenceNo><URL>http://greythorn.com.au/government-defence-emergency-jobs/leading-hand-carpenter/605190</URL><Title>Leading Hand Carpenter</Title><Message> -&gt; Job Template doesn't exists - 3575 -&gt; Advertiser Job Template Logo ID was not valid - 0</Message></Job></JobPosting></JobPostResponse>