<JobPostResponse xmlns:i="http://www.w3.org/2001/XMLSchema-instance" xmlns="http://schemas.servicestack.net/types"><ResponseCode xmlns="http://schemas.datacontract.org/2004/07/JXTPlatform.DTO.Base">SUCCESS</ResponseCode><ResponseMessage xmlns="http://schemas.datacontract.org/2004/07/JXTPlatform.DTO.Base" /><Summary><DateCreated>2016-07-21T14:33:59.04</DateCreated><FinishedDate>2016-07-21T14:34:01.247</FinishedDate><Inserted>54</Inserted><Sent>64</Sent><Updated>0</Updated><Archived>0</Archived><Failed>10</Failed></Summary><JobPosting><Job><Action>ERROR</Action><ReferenceNo>939339</ReferenceNo><URL /><Title>State Sales Manager</Title><Message> -&gt; Country is not valid -  -&gt; Location is not valid - to be advised in the future -&gt; Area is not valid -  -&gt; CountryID doesn't exists - 0 -&gt; LocationID doesn't exists - 0 -&gt; AreaID doesn't exists - 0</Message></Job><Job><Action>ERROR</Action><ReferenceNo>939345</ReferenceNo><URL /><Title>Apprentice Year 1</Title><Message> -&gt; Classification/SubClassification is not valid - Apprenticeships/Traineeships/Graduate /  -&gt; ClassificationID1 doesn't exists - 0</Message></Job><Job><Action>ERROR</Action><ReferenceNo>939359</ReferenceNo><URL /><Title>Grounds Technician</Title><Message> -&gt; Classification/SubClassification is not valid - Trades Qualified,Trades Unqualified /  -&gt; ClassificationID1 doesn't exists - 0</Message></Job><Job><Action>ERROR</Action><ReferenceNo>939378</ReferenceNo><URL /><Title>Painter</Title><Message> -&gt; Country is not valid -  -&gt; Location is not valid - New Zealand North Island -&gt; Area is not valid -  -&gt; CountryID doesn't exists - 0 -&gt; LocationID doesn't exists - 0 -&gt; AreaID doesn't exists - 0</Message></Job><Job><Action>ERROR</Action><ReferenceNo>939417</ReferenceNo><URL /><Title>Administration Trainee</Title><Message> -&gt; Classification/SubClassification is not valid - Apprenticeships/Traineeships/Graduate /  -&gt; ClassificationID1 doesn't exists - 0</Message></Job><Job><Action>ERROR</Action><ReferenceNo>939495</ReferenceNo><URL /><Title>Business Admin Traineeship</Title><Message> -&gt; Classification/SubClassification is not valid - Apprenticeships/Traineeships/Graduate /  -&gt; ClassificationID1 doesn't exists - 0</Message></Job><Job><Action>ERROR</Action><ReferenceNo>939566</ReferenceNo><URL /><Title>Horticultural Apprentice</Title><Message> -&gt; Classification/SubClassification is not valid - Apprenticeships/Traineeships/Graduate /  -&gt; ClassificationID1 doesn't exists - 0</Message></Job><Job><Action>ERROR</Action><ReferenceNo>939580</ReferenceNo><URL /><Title>Business Admin Traineeship</Title><Message> -&gt; Classification/SubClassification is not valid - Apprenticeships/Traineeships/Graduate /  -&gt; ClassificationID1 doesn't exists - 0</Message></Job><Job><Action>ERROR</Action><ReferenceNo>939617</ReferenceNo><URL /><Title>Audio Visual Service/Installation Technician</Title><Message> -&gt; Classification/SubClassification is not valid - Operations/Project Management,Trades Qualified /  -&gt; ClassificationID1 doesn't exists - 0</Message></Job><Job><Action>ERROR</Action><ReferenceNo>939621</ReferenceNo><URL /><Title>Painter Foreman</Title><Message> -&gt; Country is not valid -  -&gt; Location is not valid - New Zealand North Island -&gt; Area is not valid -  -&gt; CountryID doesn't exists - 0 -&gt; LocationID doesn't exists - 0 -&gt; AreaID doesn't exists - 0</Message></Job><Job><Action>INSERT</Action><ReferenceNo>939059</ReferenceNo><URL>http://jobs.programmed.com.au/trades-and-services-jobs/handyman/751546</URL><Title>Handyman</Title><Message> -&gt; Advertiser Job Template Logo ID was not valid - 0</Message></Job><Job><Action>INSERT</Action><ReferenceNo>939152</ReferenceNo><URL>http://jobs.programmed.com.au/hr-and-recruitment-jobs/recruitment-consultant/751572</URL><Title>Recruitment Consultant</Title><Message> -&gt; Advertiser Job Template Logo ID was not valid - 0</Message></Job><Job><Action>INSERT</Action><ReferenceNo>939194</ReferenceNo><URL>http://jobs.programmed.com.au/i-t-and-t-jobs/senior-maximo-administrator/751573</URL><Title>Senior Maximo Administrator</Title><Message> -&gt; Advertiser Job Template Logo ID was not valid - 0</Message></Job><Job><Action>INSERT</Action><ReferenceNo>939240</ReferenceNo><URL>http://jobs.programmed.com.au/trades-and-services-jobs/maintenance-level-2/751571</URL><Title>Maintenance Level 2</Title><Message> -&gt; Advertiser Job Template Logo ID was not valid - 0</Message></Job><Job><Action>INSERT</Action><ReferenceNo>939252</ReferenceNo><URL>http://jobs.programmed.com.au/i-t-and-t-jobs/project-manager/751560</URL><Title>Project Manager</Title><Message> -&gt; Advertiser Job Template Logo ID was not valid - 0</Message></Job><Job><Action>INSERT</Action><ReferenceNo>939257</ReferenceNo><URL>http://jobs.programmed.com.au/administration-jobs/after-hours-customer-service-officer/751569</URL><Title>After Hours Customer Service Officer</Title><Message> -&gt; Advertiser Job Template Logo ID was not valid - 0</Message></Job><Job><Action>INSERT</Action><ReferenceNo>939277</ReferenceNo><URL>http://jobs.programmed.com.au/sales-jobs/account-manager/751574</URL><Title>Account Manager</Title><Message> -&gt; Advertiser Job Template Logo ID was not valid - 0</Message></Job><Job><Action>INSERT</Action><ReferenceNo>939278</ReferenceNo><URL>http://jobs.programmed.com.au/sales-jobs/account-manager/751522</URL><Title>Account Manager</Title><Message> -&gt; Advertiser Job Template Logo ID was not valid - 0</Message></Job><Job><Action>INSERT</Action><ReferenceNo>939327</ReferenceNo><URL>http://jobs.programmed.com.au/trades-and-services-jobs/labourer/751565</URL><Title>Labourer</Title><Message> -&gt; Advertiser Job Template Logo ID was not valid - 0</Message></Job><Job><Action>INSERT</Action><ReferenceNo>939329</ReferenceNo><URL>http://jobs.programmed.com.au/trades-and-services-jobs/painting-contractors-for-seq-region/751566</URL><Title>Painting Contractors for SEQ Region</Title><Message> -&gt; Advertiser Job Template Logo ID was not valid - 0</Message></Job><Job><Action>INSERT</Action><ReferenceNo>939330</ReferenceNo><URL>http://jobs.programmed.com.au/trades-and-services-jobs/contract-buliders-and-carpenters/751570</URL><Title>Contract Buliders &amp; Carpenters</Title><Message> -&gt; Advertiser Job Template Logo ID was not valid - 0</Message></Job><Job><Action>INSERT</Action><ReferenceNo>939342</ReferenceNo><URL>http://jobs.programmed.com.au/trades-and-services-jobs/painter/751567</URL><Title>Painter</Title><Message> -&gt; Advertiser Job Template Logo ID was not valid - 0</Message></Job><Job><Action>INSERT</Action><ReferenceNo>939344</ReferenceNo><URL>http://jobs.programmed.com.au/trades-and-services-jobs/apprentice-year-1/751564</URL><Title>Apprentice Year 1</Title><Message> -&gt; Advertiser Job Template Logo ID was not valid - 0</Message></Job><Job><Action>INSERT</Action><ReferenceNo>939347</ReferenceNo><URL>http://jobs.programmed.com.au/trades-and-services-jobs/painter/751568</URL><Title>Painter</Title><Message> -&gt; Advertiser Job Template Logo ID was not valid - 0</Message></Job><Job><Action>INSERT</Action><ReferenceNo>939360</ReferenceNo><URL>http://jobs.programmed.com.au/i-t-and-t-jobs/project-manager/751561</URL><Title>Project Manager</Title><Message> -&gt; Advertiser Job Template Logo ID was not valid - 0</Message></Job><Job><Action>INSERT</Action><ReferenceNo>939366</ReferenceNo><URL>http://jobs.programmed.com.au/administration-jobs/client-services-coordinator/751558</URL><Title>Client Services Coordinator</Title><Message> -&gt; Advertiser Job Template Logo ID was not valid - 0</Message></Job><Job><Action>INSERT</Action><ReferenceNo>939371</ReferenceNo><URL>http://jobs.programmed.com.au/trades-and-services-jobs/painter-foreman/751563</URL><Title>Painter Foreman</Title><Message> -&gt; Advertiser Job Template Logo ID was not valid - 0</Message></Job><Job><Action>INSERT</Action><ReferenceNo>939380</ReferenceNo><URL>http://jobs.programmed.com.au/trades-and-services-jobs/grounds-maintenance-operative/751562</URL><Title>Grounds Maintenance Operative</Title><Message> -&gt; Advertiser Job Template Logo ID was not valid - 0</Message></Job><Job><Action>INSERT</Action><ReferenceNo>939388</ReferenceNo><URL>http://jobs.programmed.com.au/i-t-and-t-jobs/supervisor/751559</URL><Title>Supervisor</Title><Message> -&gt; Advertiser Job Template Logo ID was not valid - 0</Message></Job><Job><Action>INSERT</Action><ReferenceNo>939424</ReferenceNo><URL>http://jobs.programmed.com.au/trades-and-services-jobs/expressions-of-interest-hvac-technicians-and-electricians/751545</URL><Title>Expressions of Interest - HVAC Technicians and Electricians</Title><Message> -&gt; Advertiser Job Template Logo ID was not valid - 0</Message></Job><Job><Action>INSERT</Action><ReferenceNo>939429</ReferenceNo><URL>http://jobs.programmed.com.au/hr-and-recruitment-jobs/resource-specialist/751557</URL><Title>Resource Specialist</Title><Message> -&gt; Advertiser Job Template Logo ID was not valid - 0</Message></Job><Job><Action>INSERT</Action><ReferenceNo>939436</ReferenceNo><URL>http://jobs.programmed.com.au/engineering-jobs/asset-maintenance-planner/751556</URL><Title>Asset Maintenance Planner</Title><Message> -&gt; Advertiser Job Template Logo ID was not valid - 0</Message></Job><Job><Action>INSERT</Action><ReferenceNo>939453</ReferenceNo><URL>http://jobs.programmed.com.au/i-t-and-t-jobs/facilities-coordinator/751552</URL><Title>Facilities Coordinator</Title><Message> -&gt; Advertiser Job Template Logo ID was not valid - 0</Message></Job><Job><Action>INSERT</Action><ReferenceNo>939463</ReferenceNo><URL>http://jobs.programmed.com.au/construction-and-architecture-jobs/bid-writer/751536</URL><Title>Bid Writer</Title><Message> -&gt; Advertiser Job Template Logo ID was not valid - 0</Message></Job><Job><Action>INSERT</Action><ReferenceNo>939470</ReferenceNo><URL>http://jobs.programmed.com.au/trades-and-services-jobs/maintenance-level-2/751555</URL><Title>Maintenance Level 2</Title><Message> -&gt; Advertiser Job Template Logo ID was not valid - 0</Message></Job><Job><Action>INSERT</Action><ReferenceNo>939472</ReferenceNo><URL>http://jobs.programmed.com.au/sales-jobs/account-manager/751553</URL><Title>Account Manager</Title><Message> -&gt; Advertiser Job Template Logo ID was not valid - 0</Message></Job><Job><Action>INSERT</Action><ReferenceNo>939476</ReferenceNo><URL>http://jobs.programmed.com.au/trades-and-services-jobs/landscaper/751554</URL><Title>Landscaper</Title><Message> -&gt; Advertiser Job Template Logo ID was not valid - 0</Message></Job><Job><Action>INSERT</Action><ReferenceNo>939487</ReferenceNo><URL>http://jobs.programmed.com.au/trades-and-services-jobs/greenkeeper/751549</URL><Title>Greenkeeper</Title><Message> -&gt; Advertiser Job Template Logo ID was not valid - 0</Message></Job><Job><Action>INSERT</Action><ReferenceNo>939488</ReferenceNo><URL>http://jobs.programmed.com.au/trades-and-services-jobs/greenkeeper/751550</URL><Title>GREENKEEPER</Title><Message> -&gt; Advertiser Job Template Logo ID was not valid - 0</Message></Job><Job><Action>INSERT</Action><ReferenceNo>939489</ReferenceNo><URL>http://jobs.programmed.com.au/trades-and-services-jobs/groundsman/751551</URL><Title>GROUNDSMAN</Title><Message> -&gt; Advertiser Job Template Logo ID was not valid - 0</Message></Job><Job><Action>INSERT</Action><ReferenceNo>939490</ReferenceNo><URL>http://jobs.programmed.com.au/hr-and-recruitment-jobs/resourcing-specialist/751542</URL><Title>Resourcing Specialist</Title><Message> -&gt; Advertiser Job Template Logo ID was not valid - 0</Message></Job><Job><Action>INSERT</Action><ReferenceNo>939501</ReferenceNo><URL>http://jobs.programmed.com.au/trades-and-services-jobs/team-leader/751548</URL><Title>Team Leader</Title><Message> -&gt; Advertiser Job Template Logo ID was not valid - 0</Message></Job><Job><Action>INSERT</Action><ReferenceNo>939503</ReferenceNo><URL>http://jobs.programmed.com.au/sales-jobs/account-manager/751547</URL><Title>Account Manager</Title><Message> -&gt; Advertiser Job Template Logo ID was not valid - 0</Message></Job><Job><Action>INSERT</Action><ReferenceNo>939507</ReferenceNo><URL>http://jobs.programmed.com.au/i-t-and-t-jobs/project-supervisor-qa/751541</URL><Title>Project Supervisor/QA</Title><Message> -&gt; Advertiser Job Template Logo ID was not valid - 0</Message></Job><Job><Action>INSERT</Action><ReferenceNo>939509</ReferenceNo><URL>http://jobs.programmed.com.au/administration-jobs/contract-administration-assistant/751543</URL><Title>Contract Administration Assistant</Title><Message> -&gt; Advertiser Job Template Logo ID was not valid - 0</Message></Job><Job><Action>INSERT</Action><ReferenceNo>939512</ReferenceNo><URL>http://jobs.programmed.com.au/hr-and-recruitment-jobs/permanent-resourcing-specialist/751540</URL><Title>Permanent Resourcing Specialist</Title><Message> -&gt; Advertiser Job Template Logo ID was not valid - 0</Message></Job><Job><Action>INSERT</Action><ReferenceNo>939517</ReferenceNo><URL>http://jobs.programmed.com.au/hr-and-recruitment-jobs/regional-hse-advisor/751537</URL><Title>Regional HSE Advisor</Title><Message> -&gt; Advertiser Job Template Logo ID was not valid - 0</Message></Job><Job><Action>INSERT</Action><ReferenceNo>939520</ReferenceNo><URL>http://jobs.programmed.com.au/trades-and-services-jobs/qual-horticultural-tradeperson/751544</URL><Title>Qual Horticultural Tradeperson</Title><Message> -&gt; Advertiser Job Template Logo ID was not valid - 0</Message></Job><Job><Action>INSERT</Action><ReferenceNo>939523</ReferenceNo><URL>http://jobs.programmed.com.au/trades-and-services-jobs/qual-horticultural-tradeperson/751525</URL><Title>Qual Horticultural Tradeperson</Title><Message> -&gt; Advertiser Job Template Logo ID was not valid - 0</Message></Job><Job><Action>INSERT</Action><ReferenceNo>939525</ReferenceNo><URL>http://jobs.programmed.com.au/accounting-jobs/payroll-officer/751534</URL><Title>Payroll Officer</Title><Message> -&gt; Advertiser Job Template Logo ID was not valid - 0</Message></Job><Job><Action>INSERT</Action><ReferenceNo>939530</ReferenceNo><URL>http://jobs.programmed.com.au/trades-and-services-jobs/expressions-of-interest-plumbers-and-gas-fitters/751529</URL><Title>Expressions of Interest - Plumbers and Gas Fitters</Title><Message> -&gt; Advertiser Job Template Logo ID was not valid - 0</Message></Job><Job><Action>INSERT</Action><ReferenceNo>939531</ReferenceNo><URL>http://jobs.programmed.com.au/trades-and-services-jobs/expressions-of-interest-carpenters/751530</URL><Title>Expressions of Interest - Carpenters</Title><Message> -&gt; Advertiser Job Template Logo ID was not valid - 0</Message></Job><Job><Action>INSERT</Action><ReferenceNo>939532</ReferenceNo><URL>http://jobs.programmed.com.au/trades-and-services-jobs/painter/751538</URL><Title>Painter</Title><Message> -&gt; Advertiser Job Template Logo ID was not valid - 0</Message></Job><Job><Action>INSERT</Action><ReferenceNo>939533</ReferenceNo><URL>http://jobs.programmed.com.au/trades-and-services-jobs/apprentice-year-1/751532</URL><Title>Apprentice Year 1</Title><Message> -&gt; Advertiser Job Template Logo ID was not valid - 0</Message></Job><Job><Action>INSERT</Action><ReferenceNo>939536</ReferenceNo><URL>http://jobs.programmed.com.au/accounting-jobs/credit-controller/751527</URL><Title>Credit Controller</Title><Message> -&gt; Advertiser Job Template Logo ID was not valid - 0</Message></Job><Job><Action>INSERT</Action><ReferenceNo>939541</ReferenceNo><URL>http://jobs.programmed.com.au/trades-and-services-jobs/painter-foreman-1/751539</URL><Title>Painter Foreman 1</Title><Message> -&gt; Advertiser Job Template Logo ID was not valid - 0</Message></Job><Job><Action>INSERT</Action><ReferenceNo>939544</ReferenceNo><URL>http://jobs.programmed.com.au/hr-and-recruitment-jobs/injury-management-advisor/751533</URL><Title>Injury Management Advisor</Title><Message> -&gt; Advertiser Job Template Logo ID was not valid - 0</Message></Job><Job><Action>INSERT</Action><ReferenceNo>939548</ReferenceNo><URL>http://jobs.programmed.com.au/trades-and-services-jobs/grounds-maintenance-operative/751535</URL><Title>Grounds Maintenance Operative</Title><Message> -&gt; Advertiser Job Template Logo ID was not valid - 0</Message></Job><Job><Action>INSERT</Action><ReferenceNo>939555</ReferenceNo><URL>http://jobs.programmed.com.au/hr-and-recruitment-jobs/hse-manager-vic-tas/751528</URL><Title>HSE Manager - VIC / TAS</Title><Message> -&gt; Advertiser Job Template Logo ID was not valid - 0</Message></Job><Job><Action>INSERT</Action><ReferenceNo>939560</ReferenceNo><URL>http://jobs.programmed.com.au/sales-jobs/account-manager/751531</URL><Title>Account Manager</Title><Message> -&gt; Advertiser Job Template Logo ID was not valid - 0</Message></Job><Job><Action>INSERT</Action><ReferenceNo>939575</ReferenceNo><URL>http://jobs.programmed.com.au/trades-and-services-jobs/water-industry-worker-3-1/751526</URL><Title>Water Industry Worker 3/1</Title><Message> -&gt; Advertiser Job Template Logo ID was not valid - 0</Message></Job><Job><Action>INSERT</Action><ReferenceNo>939592</ReferenceNo><URL>http://jobs.programmed.com.au/trades-and-services-jobs/painter/751523</URL><Title>Painter</Title><Message> -&gt; Advertiser Job Template Logo ID was not valid - 0</Message></Job><Job><Action>INSERT</Action><ReferenceNo>939623</ReferenceNo><URL>http://jobs.programmed.com.au/trades-and-services-jobs/mechanical-fitter/751521</URL><Title>Mechanical Fitter</Title><Message> -&gt; Advertiser Job Template Logo ID was not valid - 0</Message></Job><Job><Action>INSERT</Action><ReferenceNo>939624</ReferenceNo><URL>http://jobs.programmed.com.au/trades-and-services-jobs/carpenter-foreman-4/751524</URL><Title>Carpenter Foreman 4</Title><Message> -&gt; Advertiser Job Template Logo ID was not valid - 0</Message></Job></JobPosting></JobPostResponse>